{
    "appKeys": {},
    "capabilities": [
        "configurable"
    ],
    "companyName": "mail@chernowii.com",
    "longName": "TaskWarrior Pebble",
    "projectType": "pebblejs",
    "resources": {
        "media": [
            {
                "file": "images/menu_icon.png",
                "name": "IMAGE_MENU_ICON",
                "type": "bitmap"
            },
            {
                "file": "images/logo_splash.png",
                "name": "IMAGE_LOGO_SPLASH",
                "type": "bitmap"
            },
            {
                "file": "images/tile_splash.png",
                "name": "IMAGE_TILE_SPLASH",
                "type": "bitmap"
            },
            {
                "file": "fonts/UbuntuMono-Regular.ttf",
                "name": "MONO_FONT_14",
                "type": "font"
            },
            {
                "file": "images/app_icon",
                "menuIcon": true,
                "name": "IMAGES_APP_ICON",
                "type": "png"
            }
        ]
    },
    "sdkVersion": "3",
    "shortName": "pInTheAM",
    "targetPlatforms": [
        "aplite",
        "basalt",
        "chalk"
    ],
    "uuid": "7f34ee76-7e6d-4d81-a708-03c7fe868ae2",
    "versionCode": 1,
    "versionLabel": "1.0",
    "watchapp": {
        "hiddenApp": false,
        "watchface": false
    }
}
